{"#HappyChanyeolDay": {"tweet_list": [{"text": "RT @Koreaboo: Happy Birthday Chanyeol! \ud83c\udf89\ud83c\udf82\u2764\ufe0f @weareoneEXO #HappyChanyeolDay https://t.co/GK2t79L82F", "datetime": "Mon Nov 26 17:06:39 +0000 2018"}, {"text": "RT @qtpiebyunbaek: #\ucc2c\uc5f4\uc544\uc0dd\uc77c\ucd95\ud558\ud574 Happy 27th Birthday to our little Prince, Chanyeol! Our winter blessing, so thankful to spend another November\u2026", "datetime": "Mon Nov 26 17:06:39 +0000 2018"}, {"text": "RT @soompi: Happy Birthday to #EXO's Chanyeol! #HappyChanyeolDay! \ud83c\udf89 Catch up with him: https://t.co/5EsoRu0HU0 https://t.co/lH4X2pLQ6x", "datetime": "Mon Nov 26 17:06:39 +0000 2018"}, {"text": "RT @ksoopic: Happy Birthday to Kyungsoo's number 1 hypeman, Park Chanyeol \u2764 We love you so much our happy virus, stay happy and health with\u2026", "datetime": "Mon Nov 26 17:06:39 +0000 2018"}, {"text": "Our Power \u2604.. \n\n#EXO #HappyChanyeolDay #CHANYEOL @weareoneEXO #\ucc2c\uc5f4\uc544\uc0dd\uc77c\ucd95\ud558\ud574 https://t.co/uPegRYGhjJ", "datetime": "Mon Nov 26 17:06:38 +0000 2018"}, {"text": "RT @Koreaboo: Happy Birthday Chanyeol! \ud83c\udf89\ud83c\udf82\u2764\ufe0f @weareoneEXO #HappyChanyeolDay https://t.co/GK2t79L82F", "datetime": "Mon Nov 26 17:06:38 +0000 2018"}, {"text": "RT @kpoplover727: I hope you achieve all your dreams and continue to be successful ! \n\nBirthday boy Chanyeol thank you for aspiring everyon\u2026", "datetime": "Mon Nov 26 17:06:38 +0000 2018"}, {"text": "RT @pcysarchive: he\u2019s so extra i love it. happy birthday legend #HappyChanyeolDay https://t.co/tdCjQzM8z0", "datetime": "Mon Nov 26 17:06:37 +0000 2018"}, {"text": "RT @wondeukist: this video of chanyeol celebrating his 27th birthday while wearing a deadpool costumes will stay legendary on twitter. #Hap\u2026", "datetime": "Mon Nov 26 17:06:37 +0000 2018"}, {"text": "not to be that person but i love chanyeol so much even i cant describe it with words, i just love him so much. #HappyChanyeolDay", "datetime": "Mon Nov 26 17:06:37 +0000 2018"}, {"text": "RT @dearkwonjiyong: HAPPY BIRTHDAY KING I LOVE YOU THANK YOU FOR EVERYTHING &amp; STAY HEALTHY \ud83d\udc97\ud83d\udc97\ud83d\udc97 #HappyChanyeolDay https://t.co/5vXDU5vBOd", "datetime": "Mon Nov 26 17:06:37 +0000 2018"}, {"text": "RT @pcyhqs: happy birthday to the cutest happy virus park chanyeol! we all hope you have the best day and stay healthy and happy #HappyChan\u2026", "datetime": "Mon Nov 26 17:06:37 +0000 2018"}, {"text": "RT @frealuvph: 2018 CHANYEOL DAY GIVEAWAY \u2728\n\u2013 #HappyChanyeolDay #\ucc2c\uc5f4\uc544\uc0dd\uc77c\ucd95\ud558\ud574 \n\ngiveaway ends: 12/8 \ud83d\udc8c\n\nfollow us + rt this and our pinned! \n[se\u2026", "datetime": "Mon Nov 26 17:06:37 +0000 2018"}, {"text": "RT @soompi: Happy Birthday to #EXO's Chanyeol! #HappyChanyeolDay! \ud83c\udf89 Catch up with him: https://t.co/5EsoRu0HU0 https://t.co/lH4X2pLQ6x", "datetime": "Mon Nov 26 17:06:36 +0000 2018"}, {"text": "RT @VANILIA1127: I can see your eyes and I can see your face. See your smile ever you are.\n#\ucc2c\uc5f4 #CHANYEOL \n#HAPPYCHANYEOLDAY\n#HappyLOEYDay\nh\u2026", "datetime": "Mon Nov 26 17:06:36 +0000 2018"}], "tweet_count": 710180}, "#CyberMonday": {"tweet_list": [{"text": "RT @Senators: Get 25% off your entire order today when you spend $50 at https://t.co/wty4p3FpoC and use the promo code: cybersens18.\n\n#CYBE\u2026", "datetime": "Mon Nov 26 17:06:36 +0000 2018"}, {"text": "RT @FreeEagleStu: You might also like the orcs of #Maereath. For the longest time, these creatures have been EEEEEEEEVIL for reasons. There\u2026", "datetime": "Mon Nov 26 17:06:36 +0000 2018"}, {"text": "RT @womensmarch: It\u2019s #CyberMonday. You could give your money to big businesses that don\u2019t share your values, or you can spend your money s\u2026", "datetime": "Mon Nov 26 17:06:35 +0000 2018"}, {"text": "It's Cyber Monday! Time to make up for all of the deals you missed on Black Friday. Click the link below to see what we have on!\nhttps://t.co/54tux6c2rf\n#CyberMonday  #MondayMotivation #ItsWineDrinkIt https://t.co/xtu4Vf3Leo", "datetime": "Mon Nov 26 17:06:35 +0000 2018"}, {"text": "RT @cdbaby: \ud83c\udf32 SAVE 50% on the cost of worldwide album distribution for a limited time only! Save now: https://t.co/9skp4dP16y  #cdbaby #Bla\u2026", "datetime": "Mon Nov 26 17:06:35 +0000 2018"}, {"text": "RT @BigMachine: Since it's #CyberMonday... we extended our #BlackFriday sale!\n\nGet 50% off these Christmas CD's! \ud83c\udf84\ud83c\udfb6 https://t.co/K2OG6QMDmZ", "datetime": "Mon Nov 26 17:06:35 +0000 2018"}, {"text": "#CyberMonday2018 #CyberMonday Discount code: BLACKFRIDAY \n                 https://t.co/k3lz1ZiQ3H https://t.co/HeEWe5DfA4", "datetime": "Mon Nov 26 17:06:35 +0000 2018"}, {"text": "RT @dominos: \ud83d\udea8 50% off all menu-priced pizzas when you order online now through 12/2 \ud83d\udea8 RT to bless someone's timeline with this deal. #Cybe\u2026", "datetime": "Mon Nov 26 17:06:35 +0000 2018"}, {"text": "50% OFF Stylish Silver Analog Wall Clock by Belladonna Home Decor on Storenvy. https://t.co/nS5vnWfgxp\n#CyberMondayDeals #cybermonday #MondayMotivation", "datetime": "Mon Nov 26 17:06:34 +0000 2018"}, {"text": "RT @MLBNetwork: RETWEET for a chance at a bottle of 2018 #ASG field dirt &amp; a ball signed by @ozzie and check out more items at https://t.co\u2026", "datetime": "Mon Nov 26 17:06:34 +0000 2018"}, {"text": "RT @acn_uk: It's #CyberMonday and what better way to celebrate the festive season than by changing someone's life this Christmas? &gt; https:/\u2026", "datetime": "Mon Nov 26 17:06:33 +0000 2018"}, {"text": "It's #CyberMonday and we have a very special offer - 10% off EVERYTHING at https://t.co/uZEfF0NsBc. Use code CYBERMEEPO at checkout. #Esk8 #ESkate https://t.co/DdYNsMeMrF", "datetime": "Mon Nov 26 17:06:33 +0000 2018"}, {"text": "RT @EllerCollege: #BlackFriday sales online rose 23.6% from last year, hitting a whopping $6.22 billion! In other news... Happy #CyberMonda\u2026", "datetime": "Mon Nov 26 17:06:33 +0000 2018"}, {"text": "RT @beststuff: Everything you need to know about #CyberMonday, right this way: https://t.co/h0hEaj5ZGT", "datetime": "Mon Nov 26 17:06:33 +0000 2018"}, {"text": "Try the 7-day free trial to our Master Subscription and check out the best IT skills training subscription in the industry today. #ITSkillsTraining #subscription #training #CyberMonday\n\nhttps://t.co/pjT9WIF4rt https://t.co/oUsnXyUDnZ", "datetime": "Mon Nov 26 17:06:33 +0000 2018"}], "tweet_count": 142186}, "Bernardo Bertolucci": {"tweet_list": [{"text": "RT @ArtandSlowFilm: Bernardo Bertolucci has died. A sad day for cinema. Also a day which shows how little people care abt sexual assault. A\u2026", "datetime": "Mon Nov 26 17:06:36 +0000 2018"}, {"text": "RT @ArtandSlowFilm: Bernardo Bertolucci has died. A sad day for cinema. Also a day which shows how little people care abt sexual assault. A\u2026", "datetime": "Mon Nov 26 17:06:34 +0000 2018"}, {"text": "RT @iamthatroby: everyone who says \u201crip Bernardo Bertolucci\u201d can kindly fuck off. As a director, your one job is to make everyone feel safe\u2026", "datetime": "Mon Nov 26 17:06:32 +0000 2018"}, {"text": "RT @LostInFilm: 'The Dreamers' (2003, Bernardo Bertolucci) https://t.co/TMP82adFP1", "datetime": "Mon Nov 26 17:06:30 +0000 2018"}, {"text": "RT @LostInFilm: 'The Dreamers' (2003, Bernardo Bertolucci) https://t.co/TMP82adFP1", "datetime": "Mon Nov 26 17:06:29 +0000 2018"}, {"text": "RT @sanjoynarayan: Bernardo Bertolucci: the brilliant last emperor of highbrow cinema https://t.co/crJwguOB3p", "datetime": "Mon Nov 26 17:06:26 +0000 2018"}, {"text": "RT @IndieWire: Bernardo Bertolucci, Oscar Winner and \u2018Last Tango in Paris\u2019 Director, Dead at 77 https://t.co/pSwYta7E0m https://t.co/2ynTWZ\u2026", "datetime": "Mon Nov 26 17:06:26 +0000 2018"}, {"text": "RT @BBCNewsEnts: Read about Bernardo Bertolucci's 5 key films, and the acclaim and controversy they brought https://t.co/d9t9I3qEim\ud83d\udcfd\ufe0f", "datetime": "Mon Nov 26 17:06:26 +0000 2018"}, {"text": "RT @cameron_tiff: THE CONFORMIST is how we slip into the warm bath of fascism. I hope it\u2019s not too subtle for our firehose times. Thank you\u2026", "datetime": "Mon Nov 26 17:06:23 +0000 2018"}, {"text": "RT @embalajedigital: \ud83d\udca5 Bernardo Bertolucci: the brilliant last emperor of highbrow cinema \ud83d\udcfd\ufe0f by https://t.co/QILDY7bgi8 #cine #TV #DVD #Blu\u2026", "datetime": "Mon Nov 26 17:06:22 +0000 2018"}, {"text": "RT @FilmLinc: \"I accept all interpretations of my films. The only reality is before the camera.\" R.I.P. Bernardo Bertolucci (1941-2018) htt\u2026", "datetime": "Mon Nov 26 17:06:19 +0000 2018"}, {"text": "RT @gemko: Nicolas Roeg, Ricky Jay and now Bernardo Bertolucci. The \u201ccelebrity deaths in 3s\u201d thing is stupid, but I can\u2019t recall offhand th\u2026", "datetime": "Mon Nov 26 17:06:15 +0000 2018"}, {"text": "RT @GChintamani: The filmmaker left an indelible stamp on cinema but the later day revelations of how he \u2018exploited\u2019 Maria Schneider during\u2026", "datetime": "Mon Nov 26 17:06:13 +0000 2018"}, {"text": "RT @RealEmirHan: \"In my film, there's no destiny...\"\n\n\u2022BERNARDO BERTOLUCCI\u2022\non The Conformist (1970) https://t.co/aZN4qJN782", "datetime": "Mon Nov 26 17:05:54 +0000 2018"}], "tweet_count": 58870}, "#FelizLunes": {"tweet_list": [{"text": "It's hard to dance with a devil on your back\nSo shake him off, Shake it out!!\n\n#FelizLunes #MondayMotivation", "datetime": "Mon Nov 26 17:04:40 +0000 2018"}, {"text": "@bovb51 @WALLI27 @niuracastrillon @KedmaHelena1 @La7li @lv4gab @Marieaaow @LudMarx1 @IsabelPerez1232 @VictoriaD6363 @josepaulinosan @angelicagallegs @BaironNavarete @joelcastaneda57 @May_MGWV #MondayMotivaton \ud83c\udf37 #Tm_Maya \ud83d\ude18 #FelizLunes \ud83c\udfb5 \n#happyweek \u2615\ufe0f #Friends \ud83d\udc95 @bovb51  @WALLI27 &amp; Everyone \ud83c\udf3b\n\n#EnjoyTheGo #MusicMonday #love #SmileMore \u2665\ufe0f \ud83c\udf41 https://t.co/j1LwhRFU4a", "datetime": "Mon Nov 26 17:04:18 +0000 2018"}, {"text": "New #design - Do Not Approach, Unless You Have #Coffee and #Cake \nAvailable via @redbubble \nhttps://t.co/llHw7CRvPj\n\n#coffeeshop #coffeetime #CoffeeLover #FelizLunes #MondayMotivation #Coffee  #NationalCakeDay #CyberMonday #BuenLunes #26Nov https://t.co/SkpAbjQzqN", "datetime": "Mon Nov 26 17:02:38 +0000 2018"}, {"text": "RT @bovb51: @2020sahara @WALLI27 @niuracastrillon @KedmaHelena1 @La7li @lv4gab @Marieaaow @LudMarx1 @IsabelPerez1232 @VictoriaD6363 @josepa\u2026", "datetime": "Mon Nov 26 17:02:12 +0000 2018"}, {"text": "Barcelona is the second most expensive city in Spain to make purchase \ud83d\udcb8\n\ud83d\udc49 https://t.co/ASXERDOTrS \n\n#felizlunes #barcelonahomebh https://t.co/luSqL4ECn1", "datetime": "Mon Nov 26 17:01:57 +0000 2018"}, {"text": "RT @alcalorpolitico: Show legislativo\n#CartonesDeAbraham #FelizLunes https://t.co/NjuL96ZxqS", "datetime": "Mon Nov 26 17:01:32 +0000 2018"}, {"text": "RT @bovb51: @WALLI27 @KedmaHelena1 @La7li @lv4gab @Marieaaow @LudMarx1 @IsabelPerez1232 @VictoriaD6363 @2020sahara @khanhakim_k @angelicaga\u2026", "datetime": "Mon Nov 26 17:01:10 +0000 2018"}], "tweet_count": 54922}, "#BiosCerati": {"tweet_list": [{"text": "RT @lostackles: mood #BiosCerati https://t.co/AqbnnyVBFZ", "datetime": "Mon Nov 26 16:07:34 +0000 2018"}, {"text": "So ALL Kenyan leaders advertised temuselivus on Mombasa road near Nyayo stadium? How much did the government pay for this adverts! Lee Njiiru #Checkpoint\n #BringMenHome #BiosCerati  #soultrainawards https://t.co/YU3GZk0QNz", "datetime": "Mon Nov 26 15:58:57 +0000 2018"}, {"text": "Typical Kashmir blue #sapphire , 3.04-carat, non heated, intense cornflower. It's perfect, flawless. You can have it all... anyone...\n.\n.\n.\n.\n.\n.\n.\n.\n#APiorCoisaDoMundo\u00c9 #bfc530 #BiosCerati #BomDiaBrasil #ChuvaRJ #CyberMonday #d\u00edanaranja #FelizLunes #GreyCup #Heterodino #Mas\u2026 https://t.co/4ipHAngmrD", "datetime": "Mon Nov 26 15:26:45 +0000 2018"}, {"text": "Hot #interesting hashtags #Retweet #Bambi2018 #BonPlan #BlackFriday #BorderShutdown #BuenLunes #BENDEL #Emerfalen #Boschi #BlackFridayAtGAME #BiosCerati #BasurasMarinas #followme #Bozza #Bienvenidos13 #BernardoBertolucci #Browns #BhaiVsBhai #BlueEconomy2018 #TeamEmerfalen #RT https://t.co/vyjP1Uwh4p", "datetime": "Mon Nov 26 15:20:00 +0000 2018"}, {"text": "RT @lostackles: mood #BiosCerati https://t.co/AqbnnyVBFZ", "datetime": "Mon Nov 26 14:23:42 +0000 2018"}, {"text": "RT @lostackles: mood #BiosCerati https://t.co/AqbnnyVBFZ", "datetime": "Mon Nov 26 14:20:57 +0000 2018"}, {"text": "RT @Edu_Fonk: A las 22.00... Nat GEO... \n\n#Cerati  #BiosCerati #NatGeo #GustavoCerati https://t.co/pBXoe7fvsG", "datetime": "Mon Nov 26 14:03:39 +0000 2018"}, {"text": "RT @sodafans: RT @efrain_barrera: #GraciasTotales National Geographic por #BiosCerati bravo!!!!  #Cerati #SodaStereo https://t.co/Sgb82LV0zV", "datetime": "Mon Nov 26 14:03:29 +0000 2018"}, {"text": "Sublime #BiosCerati #CeratiEterno https://t.co/3pc4giVNoY", "datetime": "Mon Nov 26 13:56:57 +0000 2018"}, {"text": "RT @Arletttwitt: I\u2019m not crying, you are \ud83d\udc9b  #BiosCerati @NatGeo_la https://t.co/xFTnmWIYgm", "datetime": "Mon Nov 26 13:25:58 +0000 2018"}, {"text": "RT @lostackles: mood #BiosCerati https://t.co/AqbnnyVBFZ", "datetime": "Mon Nov 26 13:25:48 +0000 2018"}, {"text": "#TISNews #BiosCerati is trending at 1 in world https://t.co/PnrGfKn10Q", "datetime": "Mon Nov 26 13:03:55 +0000 2018"}, {"text": "RT @AzPremierLeague: YESTERDAY MATCH | Algerian Zira FK player \ud83c\udde9\ud83c\uddff Bilal Hamdi scored his first Goal in the league @HB190 \ud83d\udc4d\n\n#Azerbaijan #Pr\u2026", "datetime": "Mon Nov 26 12:50:45 +0000 2018"}, {"text": "RT @AzPremierLeague: YESTERDAY MATCH | Algerian Zira FK player \ud83c\udde9\ud83c\uddff Bilal Hamdi scored his first Goal in the league @HB190 \ud83d\udc4d\n\n#Azerbaijan #Pr\u2026", "datetime": "Mon Nov 26 12:35:49 +0000 2018"}, {"text": "@blondieclub Genial #BiosCerati", "datetime": "Mon Nov 26 12:09:54 +0000 2018"}], "tweet_count": 39163}, "#MasterChefMx": {"tweet_list": [{"text": "RT @TLPmediagujrat: Govt+Supreme Court\nMedia + Few of Army Generals\nLibrals + Qadiaani\nGeert Wilders + European Union\nIllumanati powers +Is\u2026", "datetime": "Mon Nov 26 16:09:16 +0000 2018"}, {"text": "#GNTMgr #mystylerocksgr #food #fitness #TheVoiceGR\n#NBA #NomadsGR #Cooking #TalentoGR  #26Nov\n#HappyThanksgiving2018\n#\u0627\u0644\u0627\u062a\u062d\u0627\u062f_\u0627\u0644\u0627\u0647\u0644\u064a\n#Vikings #\u03b8\u03b5\u03c3\u03c3\u03b1\u03bb\u03bf\u03bd\u03b9\u03ba\u03b7\u03c2 #Bertolucci #MasterChefMx\n#GoPackGo\n#Gym\n.\n.\nfollow us here.\u270c\ufe0f\ud83d\ude09\n\ud83d\udc47\nhttps://t.co/3dSP8MCCCR\n\ud83d\udc47\nhttps://t.co/C3eL9fijkv\n. https://t.co/HCAIhR6Cj7", "datetime": "Mon Nov 26 15:18:29 +0000 2018"}, {"text": "RT @brincoyallavoy: #MasterChefMx The holy trinity \ud83d\udc96\u2728 https://t.co/846Vws5oF2", "datetime": "Mon Nov 26 15:12:10 +0000 2018"}], "tweet_count": 33858}, "General Motors": {"tweet_list": [{"text": "RT @CNN: JUST IN: General Motors is shutting at least five facilities in North America and slashing its staff. GM says it will reduce its s\u2026", "datetime": "Mon Nov 26 17:06:40 +0000 2018"}, {"text": "RT @lesleyabravanel: The winning is overwhelming. G.M. to Stop Production at 5 Plants in U.S. and Canada #MAGA! https://t.co/eIum3f43De", "datetime": "Mon Nov 26 17:06:39 +0000 2018"}, {"text": "RT @Carmen50: Hey #Michigan and #Ohio are you great now? \n\n#MAGA \u2066@GOP\u2069\n\nGeneral Motors to close Detroit, Ohio, Canada plants https://t.co/\u2026", "datetime": "Mon Nov 26 17:06:38 +0000 2018"}, {"text": "RT @OMGno2trump: Trump's so called greatest economy in history is losing money:\n- GM cutting $Billions, plants, jobs due to Trump's tariffs\u2026", "datetime": "Mon Nov 26 17:06:38 +0000 2018"}, {"text": "RT @kylegriffin1: General Motors plans to halt production at 3 assembly plants in Canada, Ohio, and Michigan by not allocating new products\u2026", "datetime": "Mon Nov 26 17:06:38 +0000 2018"}, {"text": "RT @LALewman: @krassenstein If you voted for Trump and now you are losing your job because of the tariffs, you voted to put yourself out of\u2026", "datetime": "Mon Nov 26 17:06:38 +0000 2018"}, {"text": "General Motors says it will cut more than 10,000 salaried staff and factory workers and close five factories by the end of next year \n\nhttps://t.co/3XwNS4x87k via #GM #generalmotors #business", "datetime": "Mon Nov 26 17:06:37 +0000 2018"}, {"text": "RT @DanaScottLO: General Motors is stopping production on 5 plants in the U.S. &amp; Canada (Ontario, Canada, Maryland, Ohio, &amp; two in Michigan\u2026", "datetime": "Mon Nov 26 17:06:37 +0000 2018"}, {"text": "RT @FOX2News: General Motors to slash 14,700 jobs in North America https://t.co/soAE8smTAz", "datetime": "Mon Nov 26 17:06:37 +0000 2018"}, {"text": "RT @mmpadellan: BREAKING: trump's tariffs on steel causing General Motors to lose $1B, now they'll layoff 14,000 jobs in North America.\n\nCa\u2026", "datetime": "Mon Nov 26 17:06:36 +0000 2018"}, {"text": "GM poised to close plants in Michigan, Ohio, Maryland, will cut 15% of salaried workers | Via USAToday https://t.co/fiZDcX7or9", "datetime": "Mon Nov 26 17:06:36 +0000 2018"}, {"text": "RT @mmpadellan: BREAKING: trump's tariffs on steel causing General Motors to lose $1B, now they'll layoff 14,000 jobs in North America.\n\nCa\u2026", "datetime": "Mon Nov 26 17:06:36 +0000 2018"}, {"text": "@realDonaldTrump Hmm, but General Motors is closing 5 factories\nand laying off all those people. Yes, good job.", "datetime": "Mon Nov 26 17:06:36 +0000 2018"}, {"text": "RT @detroitnews: UPDATE: General Motors will shutter five plants next year, including two plants in the Detroit area, as part of a restruct\u2026", "datetime": "Mon Nov 26 17:06:35 +0000 2018"}, {"text": "RT @kinsellawarren: For those wondering: in the past decade, the Canadian government gave General Motors about $14 billion, and the U.S. go\u2026", "datetime": "Mon Nov 26 17:06:35 +0000 2018"}], "tweet_count": 22626}, "#MondayMotivaton": {"tweet_list": [{"text": "RT @nywolforg: Good morning! #MondayMotivaton https://t.co/7wE3C7NqLN", "datetime": "Mon Nov 26 17:06:28 +0000 2018"}, {"text": "RT @nywolforg: Good morning! #MondayMotivaton https://t.co/7wE3C7NqLN", "datetime": "Mon Nov 26 17:06:18 +0000 2018"}, {"text": "RT @SouthINDGoogly: Not every closed door is locked\ud83c\udf88\nJust push it \u270c\n\n#MondayMotivaton #quote", "datetime": "Mon Nov 26 17:06:15 +0000 2018"}, {"text": "RT @John_KissMyBot: Isn\u2019t This So Typical Of A Hollywood Elite\n\nBarbra Streisand Believes Conservative Women Don\u2019t Think For Themselves\n\nSa\u2026", "datetime": "Mon Nov 26 17:06:04 +0000 2018"}, {"text": "@codeofvets @RobManess You know you\u2019re on the right path when the #MAGA trolls start coming for you. It\u2019s gonna be a great day! #MondayMotivaton", "datetime": "Mon Nov 26 17:06:02 +0000 2018"}, {"text": "RT @SouthINDGoogly: Not every closed door is locked\ud83c\udf88\nJust push it \u270c\n\n#MondayMotivaton #quote", "datetime": "Mon Nov 26 17:05:59 +0000 2018"}, {"text": "RT @divyaasrisri: When every action of yours is preceded by witnessing, then every move that you make in this world becomes perfect and sig\u2026", "datetime": "Mon Nov 26 17:05:57 +0000 2018"}, {"text": "#LivingInNorthIdaho  Quote that has always stood out in my mind. Hero's from all walks of life have no doubt been scared to death before putting something more important than themselves forefront. Inspiring. Make it a great week ahead #NorthIdaho  #MondayMotivaton https://t.co/OfXvhEVxy4", "datetime": "Mon Nov 26 17:05:56 +0000 2018"}, {"text": "RT @true_hindu__: Dr Roshni Tolani | Disciple of Sant Shri Asaram Bapu Ji , telling  her Divine Experience which she experienced during her\u2026", "datetime": "Mon Nov 26 17:05:35 +0000 2018"}, {"text": "RT @FvckWithBenzo: \ud83d\ude14\ud83d\udd25\ud83d\udd25\ud83d\udd25\ud83d\udd25 If you\u2019re an events organizer or club promoter? This is for you. DM me for booking details \n\n@m_loiusDJ on the dec\u2026", "datetime": "Mon Nov 26 17:05:21 +0000 2018"}, {"text": "RT @fortworthpd: #GoodMorning Fort Worth!\n\nRJ hopes you have a great day and a great week!  \n\n(Wear some antlers too.....)\n\n#MondayMotivato\u2026", "datetime": "Mon Nov 26 17:05:11 +0000 2018"}, {"text": "RT @GiGiBclub: GIVE YOURSELF PERMISSION XOXO #SuccessTRAIN #MondayMotivaton #MondayMorning  #JoyTrain @JeanetteJoy @KariJoys @loveGoldenHea\u2026", "datetime": "Mon Nov 26 17:05:10 +0000 2018"}, {"text": "It\u2019s the Holiday Season. Don\u2019t let this time of year distract you from making decisions and progress. \n\n#MondayMotivaton #MotivationMonday #motivation https://t.co/CGhjeU97nB", "datetime": "Mon Nov 26 17:05:10 +0000 2018"}, {"text": "RT @DickKingSmith: Work smarter, not harder...\n#MondayMotivaton https://t.co/pYSfZipo8D", "datetime": "Mon Nov 26 17:05:07 +0000 2018"}, {"text": "Our customers are gorgeous..\nFollow @Theaccessories3 for all your jewelry needs\n#MondayMotivaton \n#hustlersquare \n#MondayMotivation https://t.co/FKrL26leD2", "datetime": "Mon Nov 26 17:05:05 +0000 2018"}], "tweet_count": 21853}, "parlamento": {"tweet_list": [{"text": "@Docstockk @AlexSharpe64 @BBCWomansHour BTW, you might find interesting that in the SelfID law here in Portugal no definition of gender identity was included in the final text. However, the original government proposal contained this circular definition. GI occurs only for TG &amp; intersex ;) https://t.co/uymnfE3los https://t.co/AAqIJ5oQ53", "datetime": "Mon Nov 26 16:52:01 +0000 2018"}, {"text": "I like being a tourist in my own country \ud83c\udded\ud83c\uddfa\ud83d\uddfa\ud83c\udf0d\ud83e\uddf3\ud83d\udcf7 parlamento Budapest https://t.co/mdngpwB4nM", "datetime": "Mon Nov 26 16:47:36 +0000 2018"}, {"text": "london eye, big ben, parlamento \u2013 London\u00a0Picture https://t.co/curkSrZAlZ https://t.co/zh0XL2Ha1r", "datetime": "Mon Nov 26 14:33:19 +0000 2018"}, {"text": "Movimento 5 Stelle.\nOK.\n\nShe is already in Parlamento. And Lega was in charge. https://t.co/zRtGQpxlFf", "datetime": "Mon Nov 26 12:46:11 +0000 2018"}, {"text": "More than 300 lobbyists press MEPs to accept greater transparency\n@TI_EU @seap_eu @epc_eu @EpacaEU @Lobbycratie @lobbycontrol @EuropeanVoiceEV @Carnegie_Europe @WAJournal @Spinwatch @lobbyingitalia @daniel_freund @aidanosullivan @EMInternational @europeIN \nhttps://t.co/RmQJgYMzPN https://t.co/EwOlknuvzj", "datetime": "Mon Nov 26 12:28:38 +0000 2018"}, {"text": "British Parliament has the last say...\n\nhttps://t.co/gCIC7znYr1\n\n#TheresaMay #ReinoUnido #UK #Brexit #BrexitDeal #Brussels #Espa\u00f1ol #Spanish #Espanhol #ELE #LearnSpanish #FelizLunes #MondayMotivation #PracticaEspa\u00f1ol #News #UE #EU #BrexitAgreement", "datetime": "Mon Nov 26 12:01:08 +0000 2018"}, {"text": "British Parliament has the last say...\n\nhttps://t.co/IJK9Sr5oQk\n\n#TheresaMay #ReinoUnido #UK #Brexit #BrexitDeal #Brussels #Espa\u00f1ol #Spanish #Espanhol #ELE #LearnSpanish #FelizLunes #MondayMotivation #PracticaEspa\u00f1ol #News #UE #EU #BrexitAgreement", "datetime": "Mon Nov 26 11:57:03 +0000 2018"}, {"text": "Check out what I just added to my closet on Poshmark: Brioni Sportcoat 42R Blue 2 Button Parlamento Wool. https://t.co/PVEVzQ6M3i via @poshmarkapp #shopmycloset", "datetime": "Sun Nov 25 23:51:01 +0000 2018"}, {"text": "Christmas Vibes at the Canadian Parliament \ud83c\udf85 \ud83c\udf84\u2744\ufe0f @ Collina del Parlamento https://t.co/cuFTRDb7Qi", "datetime": "Sun Nov 25 18:36:47 +0000 2018"}, {"text": "RT @MacauHub: Cabo Verde Parliament approves law setting public debt limit at 60% of GDP: The Cape\u2026 https://t.co/4TiyYxP6x6", "datetime": "Sun Nov 25 15:31:52 +0000 2018"}], "tweet_count": 18318}, "Prevenir": {"tweet_list": [{"text": "Investing in #reefs to prevent their decline could generate thousands of #profits.\n\nhttps://t.co/1Yn7LJ220N https://t.co/u8LXWXwWxW", "datetime": "Mon Nov 26 14:11:00 +0000 2018"}, {"text": "\ud83d\udcf0| @lavozdeasturias reports on our flood warning system \u2b07\nhttps://t.co/UrTtOtxCs2 https://t.co/CJI28guw97", "datetime": "Mon Nov 26 12:33:55 +0000 2018"}, {"text": "@ministroMin_ Me prevenir que lamentar ;^; I Love U\ud83d\udc9c", "datetime": "Sun Nov 25 14:28:28 +0000 2018"}, {"text": "RT @Cicpc0464: #Repost @douglasricovzla with instatoolsapp \u30fb\u30fb\u30fb\nPrevenir es tarea de tod@s.\n#VENEZUELA #Instagram #Paz #Seguridad #Policia #\u2026", "datetime": "Sat Nov 24 19:27:13 +0000 2018"}, {"text": "RT @ComunidadVL: #ConsejosVL Informaci\u00f3n para prevenir Secuestros Virtuales https://t.co/FsofjxWC0V #Monitoreo \u260e 0\u20e38\u20e30\u20e30\u20e3\u25aa\ufe0f8\u20e38\u20e38\u20e3\u25aa\ufe0f8\u20e34\u20e35\u20e36\u20e3\u2026", "datetime": "Sat Nov 24 11:19:47 +0000 2018"}, {"text": "#ConsejosVL Informaci\u00f3n para prevenir Secuestros Virtuales https://t.co/FsofjxWC0V #Monitoreo \u260e 0\u20e38\u20e30\u20e30\u20e3\u25aa\ufe0f8\u20e38\u20e38\u20e3\u25aa\ufe0f8\u20e34\u20e35\u20e36\u20e3   o 1\u20e30\u20e39\u20e3", "datetime": "Sat Nov 24 10:30:17 +0000 2018"}, {"text": "RT @Cicpc0464: #Repost @douglasricovzla with instatoolsapp \u30fb\u30fb\u30fb\nPrevenir es tarea de tod@s.\n#VENEZUELA #Instagram #Paz #Seguridad #Policia #\u2026", "datetime": "Fri Nov 23 16:54:05 +0000 2018"}, {"text": "RT @Cicpc0464: #Repost @douglasricovzla with instatoolsapp \u30fb\u30fb\u30fb\nPrevenir es tarea de tod@s.\n#VENEZUELA #Instagram #Paz #Seguridad #Policia #\u2026", "datetime": "Fri Nov 23 15:00:29 +0000 2018"}, {"text": "RT @Cicpc0464: #Repost @douglasricovzla with instatoolsapp \u30fb\u30fb\u30fb\nPrevenir es tarea de tod@s.\n#VENEZUELA #Instagram #Paz #Seguridad #Policia #\u2026", "datetime": "Fri Nov 23 13:39:16 +0000 2018"}, {"text": "RT @Cicpc0464: #Repost @douglasricovzla with instatoolsapp \u30fb\u30fb\u30fb\nPrevenir es tarea de tod@s.\n#VENEZUELA #Instagram #Paz #Seguridad #Policia #\u2026", "datetime": "Fri Nov 23 13:19:54 +0000 2018"}, {"text": "#Repost @douglasricovzla with instatoolsapp \u30fb\u30fb\u30fb\nPrevenir es tarea de tod@s.\n#VENEZUELA #Instagram #Paz #Seguridad #Policia #CICPC #Criminalistica\u2026 https://t.co/r9XDxQwgmd", "datetime": "Fri Nov 23 13:18:59 +0000 2018"}, {"text": "RT @CICPC0134: #Repost @douglasricovzla (get_repost)\n\u30fb\u30fb\u30fb\nPrevenir es tarea de tod@s.\n#VENEZUELA #Instagram #Paz #Seguridad #Policia #CICPC\u2026", "datetime": "Fri Nov 23 10:51:42 +0000 2018"}, {"text": "RT @CICPC217: #Repost @douglasricovzla (get_repost)\n\u30fb\u30fb\u30fb\nPrevenir es tarea de tod@s.\n#VENEZUELA #Instagram #Paz #Seguridad #Policia #CICPC #\u2026", "datetime": "Fri Nov 23 10:36:45 +0000 2018"}, {"text": "RT @CICPC0134: #Repost @douglasricovzla (get_repost)\n\u30fb\u30fb\u30fb\nPrevenir es tarea de tod@s.\n#VENEZUELA #Instagram #Paz #Seguridad #Policia #CICPC\u2026", "datetime": "Fri Nov 23 10:36:38 +0000 2018"}, {"text": "PrEP Before and After Sex Worked as Well as Daily PrEP in Preventing HIV, New Study Finds - https://t.co/dUBel5LPUf https://t.co/R7fS1emgL0 #HealthCentral via @TheBodyDotCom", "datetime": "Fri Nov 23 06:45:18 +0000 2018"}], "tweet_count": 13649}, "#ConsultaNacional": {"tweet_list": [{"text": "RT @eje_universidad: Cantinflas Show: #RevolucionMexicana #Televisa #CamiloCatillanca #PetroEnLaW #BohemianRhapsody\u2060 \u2060 #AMLO #AmloSiempreMi\u2026", "datetime": "Mon Nov 26 03:36:08 +0000 2018"}, {"text": "Goals #ConsultaNacional https://t.co/KITAhK55bX", "datetime": "Sun Nov 25 23:46:22 +0000 2018"}, {"text": "#Voto Exhs #ConsultaNacional #repercusi\u00f3n #10programasprioritarios https://t.co/NXdnbztxrW", "datetime": "Sun Nov 25 22:51:17 +0000 2018"}, {"text": "Mooooooooorning \ud83d\uddf3\u2764\ufe0f #ConsultaNacional https://t.co/jZhI5tXkPZ", "datetime": "Sun Nov 25 16:52:57 +0000 2018"}], "tweet_count": 12952}}